textinsight/__init__.py
textinsight/core.py
textinsight_nishtha-1.0.0.dist-info/METADATA
textinsight_nishtha-1.0.0.dist-info/WHEEL
textinsight_nishtha-1.0.0.dist-info/top_level.txt
textinsight_nishtha-1.0.0.dist-info/RECORD
