Metadata-Version: 2.4
Name: textinsight-nishtha
Version: 1.0.0
Summary: A lightweight NLP toolkit for text cleaning and basic linguistic insights.
Author-email: Your Name <youremail@example.com>
Keywords: nlp,text,sentiment,preprocessing,linguistics
Classifier: Programming Language :: Python :: 3
Classifier: Topic :: Text Processing :: Linguistic
Classifier: License :: OSI Approved :: MIT License
Requires-Python: >=3.7
